<?xml version="1.0" encoding="utf-8"?>
<clothing-items>
 <clothing>
  <id>
   523158446
  </id>
  <name>
   Lacoste Umbrellas D-2513
  </name>
  <category>
   Umbrellas
  </category>
  <size>
   M
  </size>
  <color>
   Синий
  </color>
  <material>
   Нейлон
  </material>
  <price>
   551902
  </price>
  <rating>
   3.98
  </rating>
  <reviews>
   68350
  </reviews>
  <exclusive>
   no
  </exclusive>
  <sporty>
   no
  </sporty>
 </clothing>
 <clothing>
  <id>
   335630537
  </id>
  <name>
   Addidas Skirt N-1369
  </name>
  <category>
   Skirt
  </category>
  <size>
   M
  </size>
  <color>
   Красный
  </color>
  <material>
   Шерсть
  </material>
  <price>
   525848
  </price>
  <rating>
   2.94
  </rating>
  <reviews>
   674415
  </reviews>
  <new>
   +
  </new>
  <sporty>
   yes
  </sporty>
 </clothing>
 <clothing>
  <id>
   858975483
  </id>
  <name>
   Puma Belts D-2986
  </name>
  <category>
   Belts
  </category>
  <size>
   M
  </size>
  <color>
   Голубой
  </color>
  <material>
   Шелк
  </material>
  <price>
   819256
  </price>
  <rating>
   4.65
  </rating>
  <reviews>
   423759
  </reviews>
  <exclusive>
   no
  </exclusive>
 </clothing>
 <clothing>
  <id>
   216954946
  </id>
  <name>
   Addidas Skirt A-1661
  </name>
  <category>
   Skirt
  </category>
  <size>
   XXL
  </size>
  <color>
   Фиолетовый
  </color>
  <material>
   Шерсть
  </material>
  <price>
   462385
  </price>
  <rating>
   2.36
  </rating>
  <reviews>
   768462
  </reviews>
  <new>
   -
  </new>
 </clothing>
 <clothing>
  <id>
   262327842
  </id>
  <name>
   Vans T-shirt U-6018
  </name>
  <category>
   T-shirt
  </category>
  <size>
   L
  </size>
  <color>
   Желтый
  </color>
  <material>
   Вискоза
  </material>
  <price>
   102648
  </price>
  <rating>
   3.38
  </rating>
  <reviews>
   96420
  </reviews>
  <new>
   +
  </new>
  <exclusive>
   yes
  </exclusive>
  <sporty>
   yes
  </sporty>
 </clothing>
 <clothing>
  <id>
   157150818
  </id>
  <name>
   New Balance Jeans T-5981
  </name>
  <category>
   Jeans
  </category>
  <size>
   XXL
  </size>
  <color>
   Красный
  </color>
  <material>
   Вискоза
  </material>
  <price>
   357830
  </price>
  <rating>
   2.98
  </rating>
  <reviews>
   909941
  </reviews>
  <exclusive>
   no
  </exclusive>
 </clothing>
 <clothing>
  <id>
   132372665
  </id>
  <name>
   Asics Handbags T-8419
  </name>
  <category>
   Handbags
  </category>
  <size>
   XXL
  </size>
  <color>
   Голубой
  </color>
  <material>
   Шерсть
  </material>
  <price>
   186057
  </price>
  <rating>
   1.11
  </rating>
  <reviews>
   492726
  </reviews>
  <new>
   -
  </new>
 </clothing>
 <clothing>
  <id>
   766730774
  </id>
  <name>
   Nike Skirt B-4015
  </name>
  <category>
   Skirt
  </category>
  <size>
   XL
  </size>
  <color>
   Красный
  </color>
  <material>
   Полиэстер
  </material>
  <price>
   892247
  </price>
  <rating>
   2.12
  </rating>
  <reviews>
   199018
  </reviews>
  <sporty>
   yes
  </sporty>
 </clothing>
 <clothing>
  <id>
   321817096
  </id>
  <name>
   Fila Shoes L-2075
  </name>
  <category>
   Shoes
  </category>
  <size>
   M
  </size>
  <color>
   Красный
  </color>
  <material>
   Кожа
  </material>
  <price>
   540924
  </price>
  <rating>
   1.42
  </rating>
  <reviews>
   620497
  </reviews>
  <new>
   -
  </new>
  <exclusive>
   yes
  </exclusive>
  <sporty>
   yes
  </sporty>
 </clothing>
 <clothing>
  <id>
   552321766
  </id>
  <name>
   Reebok Gloves P-6202
  </name>
  <category>
   Gloves
  </category>
  <size>
   S
  </size>
  <color>
   Голубой
  </color>
  <material>
   Хлопок
  </material>
  <price>
   630710
  </price>
  <rating>
   1.95
  </rating>
  <reviews>
   320337
  </reviews>
  <new>
   +
  </new>
  <exclusive>
   no
  </exclusive>
  <sporty>
   no
  </sporty>
 </clothing>
 <clothing>
  <id>
   129593189
  </id>
  <name>
   Nike Gloves U-9160
  </name>
  <category>
   Gloves
  </category>
  <size>
   M
  </size>
  <color>
   Фиолетовый
  </color>
  <material>
   Лен
  </material>
  <price>
   210071
  </price>
  <rating>
   4.92
  </rating>
  <reviews>
   242746
  </reviews>
  <new>
   -
  </new>
  <exclusive>
   yes
  </exclusive>
 </clothing>
 <clothing>
  <id>
   247688022
  </id>
  <name>
   Fila Jacket M-5818
  </name>
  <category>
   Jacket
  </category>
  <size>
   S
  </size>
  <color>
   Красный
  </color>
  <material>
   Хлопок
  </material>
  <price>
   579048
  </price>
  <rating>
   2.42
  </rating>
  <reviews>
   876576
  </reviews>
  <exclusive>
   no
  </exclusive>
 </clothing>
 <clothing>
  <id>
   192361790
  </id>
  <name>
   Under Armour Shirt X-8533
  </name>
  <category>
   Shirt
  </category>
  <size>
   S
  </size>
  <color>
   Зеленый
  </color>
  <material>
   Вискоза
  </material>
  <price>
   117382
  </price>
  <rating>
   1.81
  </rating>
  <reviews>
   589099
  </reviews>
  <new>
   -
  </new>
 </clothing>
 <clothing>
  <id>
   693291945
  </id>
  <name>
   Ellesse Hat Y-9229
  </name>
  <category>
   Hat
  </category>
  <size>
   XL
  </size>
  <color>
   Красный
  </color>
  <material>
   Нейлон
  </material>
  <price>
   551072
  </price>
  <rating>
   2.38
  </rating>
  <reviews>
   249336
  </reviews>
  <exclusive>
   no
  </exclusive>
  <sporty>
   no
  </sporty>
 </clothing>
 <clothing>
  <id>
   751475989
  </id>
  <name>
   Nike Blouse L-6199
  </name>
  <category>
   Blouse
  </category>
  <size>
   S
  </size>
  <color>
   Желтый
  </color>
  <material>
   Кожа
  </material>
  <price>
   223785
  </price>
  <rating>
   3.08
  </rating>
  <reviews>
   350426
  </reviews>
  <exclusive>
   no
  </exclusive>
  <sporty>
   yes
  </sporty>
 </clothing>
 <clothing>
  <id>
   242056540
  </id>
  <name>
   Brooks Skirt G-6532
  </name>
  <category>
   Skirt
  </category>
  <size>
   XL
  </size>
  <color>
   Синий
  </color>
  <material>
   Шелк
  </material>
  <price>
   370370
  </price>
  <rating>
   3.57
  </rating>
  <reviews>
   290242
  </reviews>
  <new>
   -
  </new>
  <exclusive>
   no
  </exclusive>
 </clothing>
 <clothing>
  <id>
   327917590
  </id>
  <name>
   Asics Socks R-6633
  </name>
  <category>
   Socks
  </category>
  <size>
   L
  </size>
  <color>
   Зеленый
  </color>
  <material>
   Кожа
  </material>
  <price>
   284101
  </price>
  <rating>
   2.24
  </rating>
  <reviews>
   8396
  </reviews>
  <new>
   -
  </new>
  <exclusive>
   no
  </exclusive>
  <sporty>
   no
  </sporty>
 </clothing>
 <clothing>
  <id>
   705795114
  </id>
  <name>
   Reebok Shoes R-5602
  </name>
  <category>
   Shoes
  </category>
  <size>
   XXL
  </size>
  <color>
   Желтый
  </color>
  <material>
   Нейлон
  </material>
  <price>
   410485
  </price>
  <rating>
   4.1
  </rating>
  <reviews>
   503139
  </reviews>
  <new>
   +
  </new>
  <sporty>
   yes
  </sporty>
 </clothing>
 <clothing>
  <id>
   494435945
  </id>
  <name>
   Brooks Umbrellas P-7131
  </name>
  <category>
   Umbrellas
  </category>
  <size>
   XL
  </size>
  <color>
   Фиолетовый
  </color>
  <material>
   Хлопок
  </material>
  <price>
   614111
  </price>
  <rating>
   2.51
  </rating>
  <reviews>
   259743
  </reviews>
  <sporty>
   yes
  </sporty>
 </clothing>
 <clothing>
  <id>
   170471875
  </id>
  <name>
   Asics Socks J-7476
  </name>
  <category>
   Socks
  </category>
  <size>
   S
  </size>
  <color>
   Фиолетовый
  </color>
  <material>
   Вискоза
  </material>
  <price>
   687640
  </price>
  <rating>
   3.46
  </rating>
  <reviews>
   295044
  </reviews>
  <exclusive>
   no
  </exclusive>
  <sporty>
   yes
  </sporty>
 </clothing>
 <clothing>
  <id>
   582720371
  </id>
  <name>
   New Balance Shirt L-8494
  </name>
  <category>
   Shirt
  </category>
  <size>
   M
  </size>
  <color>
   Фиолетовый
  </color>
  <material>
   Полиэстер
  </material>
  <price>
   127963
  </price>
  <rating>
   3.75
  </rating>
  <reviews>
   999530
  </reviews>
  <exclusive>
   no
  </exclusive>
  <sporty>
   no
  </sporty>
 </clothing>
 <clothing>
  <id>
   621532974
  </id>
  <name>
   Vans Umbrellas W-8442
  </name>
  <category>
   Umbrellas
  </category>
  <size>
   L
  </size>
  <color>
   Голубой
  </color>
  <material>
   Вискоза
  </material>
  <price>
   423746
  </price>
  <rating>
   4.44
  </rating>
  <reviews>
   90166
  </reviews>
  <new>
   +
  </new>
  <exclusive>
   no
  </exclusive>
 </clothing>
 <clothing>
  <id>
   656134184
  </id>
  <name>
   Converse Jeans K-8672
  </name>
  <category>
   Jeans
  </category>
  <size>
   L
  </size>
  <color>
   Оранжевый
  </color>
  <material>
   Шерсть
  </material>
  <price>
   100396
  </price>
  <rating>
   4.27
  </rating>
  <reviews>
   360227
  </reviews>
  <new>
   -
  </new>
 </clothing>
 <clothing>
  <id>
   275537042
  </id>
  <name>
   DC Gloves D-4927
  </name>
  <category>
   Gloves
  </category>
  <size>
   S
  </size>
  <color>
   Красный
  </color>
  <material>
   Полиэстер
  </material>
  <price>
   461135
  </price>
  <rating>
   3.97
  </rating>
  <reviews>
   182797
  </reviews>
  <exclusive>
   yes
  </exclusive>
  <sporty>
   yes
  </sporty>
 </clothing>
 <clothing>
  <id>
   560171163
  </id>
  <name>
   Brooks T-shirt E-4503
  </name>
  <category>
   T-shirt
  </category>
  <size>
   XL
  </size>
  <color>
   Голубой
  </color>
  <material>
   Шерсть
  </material>
  <price>
   644708
  </price>
  <rating>
   4.61
  </rating>
  <reviews>
   683861
  </reviews>
  <sporty>
   no
  </sporty>
 </clothing>
 <clothing>
  <id>
   857114023
  </id>
  <name>
   Nike Shirt P-4800
  </name>
  <category>
   Shirt
  </category>
  <size>
   XL
  </size>
  <color>
   Оранжевый
  </color>
  <material>
   Полиэстер
  </material>
  <price>
   775780
  </price>
  <rating>
   4.88
  </rating>
  <reviews>
   687573
  </reviews>
 </clothing>
 <clothing>
  <id>
   132430318
  </id>
  <name>
   Addidas Shoes U-2441
  </name>
  <category>
   Shoes
  </category>
  <size>
   XXL
  </size>
  <color>
   Красный
  </color>
  <material>
   Хлопок
  </material>
  <price>
   162614
  </price>
  <rating>
   3.55
  </rating>
  <reviews>
   319231
  </reviews>
  <sporty>
   no
  </sporty>
 </clothing>
 <clothing>
  <id>
   123729816
  </id>
  <name>
   New Balance Umbrellas I-4061
  </name>
  <category>
   Umbrellas
  </category>
  <size>
   M
  </size>
  <color>
   Зеленый
  </color>
  <material>
   Шерсть
  </material>
  <price>
   894707
  </price>
  <rating>
   4.54
  </rating>
  <reviews>
   353514
  </reviews>
  <new>
   +
  </new>
  <exclusive>
   no
  </exclusive>
 </clothing>
 <clothing>
  <id>
   124948541
  </id>
  <name>
   DC Pants F-4814
  </name>
  <category>
   Pants
  </category>
  <size>
   S
  </size>
  <color>
   Оранжевый
  </color>
  <material>
   Кожа
  </material>
  <price>
   978272
  </price>
  <rating>
   1.6
  </rating>
  <reviews>
   891497
  </reviews>
  <new>
   -
  </new>
 </clothing>
 <clothing>
  <id>
   854840176
  </id>
  <name>
   Lacoste Handbags M-7813
  </name>
  <category>
   Handbags
  </category>
  <size>
   L
  </size>
  <color>
   Желтый
  </color>
  <material>
   Шелк
  </material>
  <price>
   419842
  </price>
  <rating>
   2.49
  </rating>
  <reviews>
   355065
  </reviews>
  <exclusive>
   no
  </exclusive>
 </clothing>
 <clothing>
  <id>
   313850597
  </id>
  <name>
   New Balance Umbrellas V-8574
  </name>
  <category>
   Umbrellas
  </category>
  <size>
   M
  </size>
  <color>
   Зеленый
  </color>
  <material>
   Кожа
  </material>
  <price>
   718862
  </price>
  <rating>
   3.57
  </rating>
  <reviews>
   999810
  </reviews>
  <new>
   -
  </new>
  <exclusive>
   yes
  </exclusive>
 </clothing>
 <clothing>
  <id>
   803266902
  </id>
  <name>
   Ellesse Jacket W-8350
  </name>
  <category>
   Jacket
  </category>
  <size>
   L
  </size>
  <color>
   Фиолетовый
  </color>
  <material>
   Шелк
  </material>
  <price>
   692440
  </price>
  <rating>
   4.05
  </rating>
  <reviews>
   574965
  </reviews>
  <new>
   +
  </new>
 </clothing>
 <clothing>
  <id>
   379580951
  </id>
  <name>
   Nike Belts F-6690
  </name>
  <category>
   Belts
  </category>
  <size>
   XXL
  </size>
  <color>
   Голубой
  </color>
  <material>
   Шерсть
  </material>
  <price>
   492432
  </price>
  <rating>
   1.33
  </rating>
  <reviews>
   558922
  </reviews>
  <new>
   -
  </new>
  <sporty>
   no
  </sporty>
 </clothing>
 <clothing>
  <id>
   141629180
  </id>
  <name>
   Asics T-shirt G-3600
  </name>
  <category>
   T-shirt
  </category>
  <size>
   XXL
  </size>
  <color>
   Зеленый
  </color>
  <material>
   Лен
  </material>
  <price>
   867142
  </price>
  <rating>
   4.14
  </rating>
  <reviews>
   767554
  </reviews>
  <new>
   +
  </new>
  <exclusive>
   yes
  </exclusive>
  <sporty>
   no
  </sporty>
 </clothing>
 <clothing>
  <id>
   178601262
  </id>
  <name>
   Addidas Belts O-5581
  </name>
  <category>
   Belts
  </category>
  <size>
   XXL
  </size>
  <color>
   Зеленый
  </color>
  <material>
   Шелк
  </material>
  <price>
   121126
  </price>
  <rating>
   4.9
  </rating>
  <reviews>
   254847
  </reviews>
  <new>
   -
  </new>
  <exclusive>
   yes
  </exclusive>
  <sporty>
   yes
  </sporty>
 </clothing>
 <clothing>
  <id>
   926670240
  </id>
  <name>
   Nike Dress G-8406
  </name>
  <category>
   Dress
  </category>
  <size>
   M
  </size>
  <color>
   Голубой
  </color>
  <material>
   Шелк
  </material>
  <price>
   567272
  </price>
  <rating>
   2.22
  </rating>
  <reviews>
   294023
  </reviews>
  <new>
   +
  </new>
 </clothing>
 <clothing>
  <id>
   794217032
  </id>
  <name>
   New Balance Shirt R-5206
  </name>
  <category>
   Shirt
  </category>
  <size>
   XL
  </size>
  <color>
   Синий
  </color>
  <material>
   Лен
  </material>
  <price>
   510518
  </price>
  <rating>
   1.76
  </rating>
  <reviews>
   23808
  </reviews>
  <exclusive>
   no
  </exclusive>
  <sporty>
   yes
  </sporty>
 </clothing>
 <clothing>
  <id>
   208201133
  </id>
  <name>
   Addidas Dress O-9885
  </name>
  <category>
   Dress
  </category>
  <size>
   XL
  </size>
  <color>
   Оранжевый
  </color>
  <material>
   Шерсть
  </material>
  <price>
   395660
  </price>
  <rating>
   1.68
  </rating>
  <reviews>
   839842
  </reviews>
  <new>
   -
  </new>
  <exclusive>
   yes
  </exclusive>
  <sporty>
   yes
  </sporty>
 </clothing>
</clothing-items>
